{"id": "198066", "home": {"id": "205", "name": "Brazil", "tla": "BRA", "crest": "https://a.espncdn.com/i/teamlogos/countries/500/bra.png", "rank": null}, "away": {"id": "660", "name": "United States", "tla": "USA", "crest": "https://a.espncdn.com/i/teamlogos/countries/500/usa.png", "rank": null}, "utcDate": "1994-07-04T07:00Z", "status": "FINISHED", "score": {"home": 1, "away": 0}, "group": null, "espnMatched": true, "espnId": "198066", "events": [{"minute": "73'", "type": "Goal", "side": "home", "player": "", "text": ""}], "odds": null, "attendance": null, "venue": {"name": "Stanford", "city": "Palo Alto", "country": "USA", "image": "https://services.arcgisonline.com/arcgis/rest/services/World_Imagery/MapServer/export?bbox=-122.1746,37.4259,-122.1654,37.429100000000005&bboxSR=4326&imageSR=4326&size=1280,440&format=jpg&f=image", "capacity": null, "surface": null}, "weather": {}}