{"id": "760457", "home": {"id": "478", "name": "France", "tla": "FRA", "crest": "https://a.espncdn.com/i/teamlogos/countries/500/fra.png", "rank": null}, "away": {"id": "4375", "name": "Iraq", "tla": "IRQ", "crest": "https://a.espncdn.com/i/teamlogos/countries/500/irq.png", "rank": null}, "utcDate": "2026-06-22T21:00Z", "status": "FINISHED", "score": {"home": 3, "away": 0}, "group": null, "espnMatched": true, "espnId": "760457", "events": [{"minute": "6'", "type": "Yellow Card", "side": "away", "player": "Amir Al-Ammari", "text": "Amir Al Ammari (Iraq) is shown the yellow card for a bad foul."}, {"minute": "14'", "type": "Goal", "side": "home", "player": "Kylian Mbapp\u00e9", "text": "Goal! France 1, Iraq 0. Kylian Mbapp\u00e9 (France) left footed shot from outside the box to the bottom left corner. Assisted by Michael Olise."}, {"minute": "54'", "type": "Goal", "side": "home", "player": "Kylian Mbapp\u00e9", "text": "Goal! France 2, Iraq 0. Kylian Mbapp\u00e9 (France) right footed shot from the centre of the box to the bottom right corner. Assisted by Ousmane Demb\u00e9l\u00e9."}, {"minute": "66'", "type": "Goal", "side": "home", "player": "Ousmane Demb\u00e9l\u00e9", "text": "Goal! France 3, Iraq 0. Ousmane Demb\u00e9l\u00e9 (France) right footed shot from the centre of the box to the bottom left corner. Assisted by Michael Olise with a through ball."}], "odds": {"provider": "DraftKings", "home": 1.08, "draw": 12.0, "away": 26.0}, "attendance": null, "venue": {"name": "Lincoln Financial Field", "city": "Philadelphia, Pennsylvania", "country": "USA", "image": "https://services.arcgisonline.com/arcgis/rest/services/World_Imagery/MapServer/export?bbox=-75.1721,39.899233329999994,-75.16290000000001,39.90243333&bboxSR=4326&imageSR=4326&size=1280,440&format=jpg&f=image", "capacity": null, "surface": null}, "weather": {"temp": 28.3, "humidity": 69, "wind": 11.2, "alt": 12.0}, "stats": {"home": {"foulsCommitted": "8", "yellowCards": "0", "redCards": "0", "offsides": "1", "wonCorners": "4", "saves": "0", "possessionPct": "55.6", "totalShots": "19", "shotsOnTarget": "5", "shotPct": "0.3", "penaltyKickGoals": "0", "penaltyKickShots": "0", "accuratePasses": "540", "totalPasses": "603", "passPct": "0.9", "accurateCrosses": "2", "totalCrosses": "14", "crossPct": "0.1", "totalLongBalls": "30", "accurateLongBalls": "17", "longballPct": "0.6", "blockedShots": "4", "effectiveTackles": "9", "totalTackles": "14", "tacklePct": "0.6", "interceptions": "5", "effectiveClearance": "9", "totalClearance": "9"}, "away": {"foulsCommitted": "4", "yellowCards": "1", "redCards": "0", "offsides": "0", "wonCorners": "2", "saves": "2", "possessionPct": "44.4", "totalShots": "4", "shotsOnTarget": "0", "shotPct": "0.0", "penaltyKickGoals": "0", "penaltyKickShots": "0", "accuratePasses": "413", "totalPasses": "481", "passPct": "0.9", "accurateCrosses": "4", "totalCrosses": "9", "crossPct": "0.4", "totalLongBalls": "51", "accurateLongBalls": "21", "longballPct": "0.4", "blockedShots": "1", "effectiveTackles": "8", "totalTackles": "16", "tacklePct": "0.5", "interceptions": "10", "effectiveClearance": "28", "totalClearance": "28"}}, "subs": {"home": [{"min": "68'", "in": "D\u00e9sir\u00e9 Dou\u00e9", "inPhoto": "https://r2.thesportsdb.com/images/media/player/thumb/70imvk1770216646.jpg", "out": "Ousmane Demb\u00e9l\u00e9", "outPhoto": "https://r2.thesportsdb.com/images/media/player/thumb/2w39ps1778803599.jpg", "reason": null}, {"min": "68'", "in": "Rayan Cherki", "inPhoto": "https://r2.thesportsdb.com/images/media/player/thumb/7eiohx1778803238.jpg", "out": "Michael Olise", "outPhoto": "https://r2.thesportsdb.com/images/media/player/thumb/kumigl1778817330.jpg", "reason": null}, {"min": "83'", "in": "Maghnes Akliouche", "inPhoto": "https://r2.thesportsdb.com/images/media/player/thumb/f4nucz1778802906.jpg", "out": "Bradley Barcola", "outPhoto": "https://r2.thesportsdb.com/images/media/player/thumb/y3v68c1778803099.jpg", "reason": null}, {"min": "83'", "in": "Malo Gusto", "inPhoto": "https://r2.thesportsdb.com/images/media/player/thumb/vpwax71778804258.jpg", "out": "Jules Kound\u00e9", "outPhoto": "https://r2.thesportsdb.com/images/media/player/thumb/ghod9q1778805401.jpg", "reason": null}, {"min": "90'+1'", "in": "Marcus Thuram", "inPhoto": "https://r2.thesportsdb.com/images/media/player/thumb/qo7y1v1724515703.jpg", "out": "Kylian Mbapp\u00e9", "outPhoto": "https://r2.thesportsdb.com/images/media/player/thumb/v08cj31778816426.jpg", "reason": null}], "away": [{"min": "26'", "in": "Ali Al-Hamadi", "inPhoto": "https://r2.thesportsdb.com/images/media/player/thumb/kwj85e1667753198.jpg", "out": "Aymen Hussein", "outPhoto": "https://r2.thesportsdb.com/images/media/player/thumb/ikbaqs1780442913.jpg", "reason": "injury"}, {"min": "60'", "in": "Rebin Sulaka", "inPhoto": "https://r2.thesportsdb.com/images/media/player/thumb/kuvak91780463116.jpg", "out": "Zaid Tahseen", "outPhoto": "https://r2.thesportsdb.com/images/media/player/thumb/3m6pe31780463304.jpg", "reason": null}, {"min": "60'", "in": "Youssef Amyn", "inPhoto": "https://r2.thesportsdb.com/images/media/player/thumb/prr9521780440625.jpg", "out": "Zaid Ismael", "outPhoto": null, "reason": null}, {"min": "68'", "in": "Aimar Sher", "inPhoto": "https://r2.thesportsdb.com/images/media/player/thumb/tuyc4f1631797563.jpg", "out": "Amir Al-Ammari", "outPhoto": "https://r2.thesportsdb.com/images/media/player/thumb/l4yhxn1718051391.jpg", "reason": null}, {"min": "69'", "in": "Marko Farji", "inPhoto": "https://r2.thesportsdb.com/images/media/player/thumb/7cnypv1780441522.jpg", "out": "Ibrahim Bayesh", "outPhoto": "https://r2.thesportsdb.com/images/media/player/thumb/uun9la1780440853.jpg", "reason": null}]}, "form": {"home": [{"r": "W", "score": "2-1", "opp": "BRA", "atVs": "@", "date": "2026-03-26"}, {"r": "W", "score": "3-1", "opp": "COL", "atVs": "@", "date": "2026-03-29"}, {"r": "L", "score": "2-1", "opp": "CIV", "atVs": "vs", "date": "2026-06-04"}, {"r": "W", "score": "3-1", "opp": "NIR", "atVs": "vs", "date": "2026-06-08"}, {"r": "W", "score": "3-1", "opp": "SEN", "atVs": "vs", "date": "2026-06-16"}], "away": [{"r": "W", "score": "2-1", "opp": "BOL", "atVs": "vs", "date": "2026-04-01"}, {"r": "W", "score": "1-0", "opp": "AND", "atVs": "vs", "date": "2026-05-29"}, {"r": "D", "score": "1-1", "opp": "ESP", "atVs": "@", "date": "2026-06-04"}, {"r": "L", "score": "2-0", "opp": "VEN", "atVs": "vs", "date": "2026-06-10"}, {"r": "L", "score": "4-1", "opp": "NOR", "atVs": "vs", "date": "2026-06-16"}]}, "h2h": null, "shootout": null}