{"id": "633847", "home": {"id": "202", "name": "Argentina", "tla": "ARG", "crest": "https://a.espncdn.com/i/teamlogos/countries/500/arg.png", "rank": null}, "away": {"id": "477", "name": "Croatia", "tla": "CRO", "crest": "https://a.espncdn.com/i/teamlogos/countries/500/cro.png", "rank": null}, "utcDate": "2022-12-13T19:00Z", "status": "FINISHED", "score": {"home": 3, "away": 0}, "group": null, "espnMatched": true, "espnId": "633847", "events": [{"minute": "32'", "type": "Yellow Card", "side": "away", "player": "Dominik Livakovic", "text": "Dominik Livakovic (Croatia) is shown the yellow card for a bad foul."}, {"minute": "32'", "type": "Yellow Card", "side": "away", "player": "Mateo Kovacic", "text": "Mateo Kovacic (Croatia) is shown the yellow card."}, {"minute": "34'", "type": "Penalty - Scored", "side": "home", "player": "Lionel Messi", "text": "Goal!  Argentina 1, Croatia 0. Lionel Messi (Argentina) converts the penalty with a left footed shot to the top right corner."}, {"minute": "39'", "type": "Goal - Volley", "side": "home", "player": "Juli\u00e1n \u00c1lvarez", "text": "Goal!  Argentina 2, Croatia 0. Juli\u00e1n \u00c1lvarez (Argentina) right footed shot from very close range to the bottom left corner    following a fast break."}, {"minute": "68'", "type": "Yellow Card", "side": "home", "player": "Cristian Romero", "text": "Cristian Romero (Argentina) is shown the yellow card for a bad foul."}, {"minute": "69'", "type": "Goal", "side": "home", "player": "Juli\u00e1n \u00c1lvarez", "text": "Goal!  Argentina 3, Croatia 0. Juli\u00e1n \u00c1lvarez (Argentina) right footed shot from the centre of the box to the centre of the goal. Assisted by Lionel Messi."}, {"minute": "71'", "type": "Yellow Card", "side": "home", "player": "Nicol\u00e1s Otamendi", "text": "Nicol\u00e1s Otamendi (Argentina) is shown the yellow card."}], "odds": null, "attendance": null, "venue": {"name": "Lusail Stadium", "city": "Lusail", "country": "Qatar", "image": "https://services.arcgisonline.com/arcgis/rest/services/World_Imagery/MapServer/export?bbox=51.485788889999995,25.41926111,51.49498889,25.42246111&bboxSR=4326&imageSR=4326&size=1280,440&format=jpg&f=image", "capacity": null, "surface": null}, "weather": {}, "stats": {"home": {"foulsCommitted": "15", "yellowCards": "2", "redCards": "0", "offsides": "1", "wonCorners": "2", "saves": "3", "possessionPct": "39.2", "totalShots": "9", "shotsOnTarget": "7", "shotPct": "0.8", "penaltyKickGoals": "1", "penaltyKickShots": "1", "accuratePasses": "333", "totalPasses": "399", "passPct": "0.8", "accurateCrosses": "1", "totalCrosses": "6", "crossPct": "0.2", "totalLongBalls": "43", "accurateLongBalls": "20", "longballPct": "0.5", "blockedShots": "1", "effectiveTackles": "9", "totalTackles": "22", "tacklePct": "0.4", "interceptions": "8", "effectiveClearance": "21", "totalClearance": "21"}, "away": {"foulsCommitted": "8", "yellowCards": "2", "redCards": "0", "offsides": "0", "wonCorners": "4", "saves": "4", "possessionPct": "60.8", "totalShots": "12", "shotsOnTarget": "2", "shotPct": "0.2", "penaltyKickGoals": "0", "penaltyKickShots": "0", "accuratePasses": "531", "totalPasses": "607", "passPct": "0.9", "accurateCrosses": "4", "totalCrosses": "20", "crossPct": "0.2", "totalLongBalls": "31", "accurateLongBalls": "17", "longballPct": "0.5", "blockedShots": "3", "effectiveTackles": "15", "totalTackles": "19", "tacklePct": "0.8", "interceptions": "5", "effectiveClearance": "7", "totalClearance": "7"}}, "subs": {"home": [{"min": "62'", "in": "Lisandro Mart\u00ednez", "inPhoto": "https://a.espncdn.com/i/headshots/soccer/players/full/233937.png", "out": "Leandro Paredes", "outPhoto": "https://r2.thesportsdb.com/images/media/player/thumb/32tyaf1780010678.jpg", "reason": null}, {"min": "74'", "in": "Exequiel Palacios", "inPhoto": "https://r2.thesportsdb.com/images/media/player/thumb/yteipb1780010763.jpg", "out": "Rodrigo De Paul", "outPhoto": "https://r2.thesportsdb.com/images/media/player/thumb/1dd1xh1770024012.jpg", "reason": null}, {"min": "74'", "in": "Paulo Dybala", "inPhoto": null, "out": "Juli\u00e1n \u00c1lvarez", "outPhoto": "https://r2.thesportsdb.com/images/media/player/thumb/rm3tj11741979331.jpg", "reason": null}, {"min": "86'", "in": "\u00c1ngel Correa", "inPhoto": null, "out": "Alexis Mac Allister", "outPhoto": "https://r2.thesportsdb.com/images/media/player/thumb/9n5dnd1751999911.jpg", "reason": null}, {"min": "86'", "in": "Juan Foyth", "inPhoto": null, "out": "Nahuel Molina", "outPhoto": "https://r2.thesportsdb.com/images/media/player/thumb/uhc6mv1719036284.jpg", "reason": null}], "away": [{"min": "45'", "in": "Mislav Orsic", "inPhoto": "https://r2.thesportsdb.com/images/media/player/thumb/mycyce1622023343.jpg", "out": "Borna Sosa", "outPhoto": null, "reason": null}, {"min": "45'", "in": "Nikola Vlasic", "inPhoto": "https://r2.thesportsdb.com/images/media/player/thumb/on2oja1622020774.jpg", "out": "Mario Pasalic", "outPhoto": "https://r2.thesportsdb.com/images/media/player/thumb/u3di9z1546032437.jpg", "reason": null}, {"min": "50'", "in": "Bruno Petkovic", "inPhoto": "https://r2.thesportsdb.com/images/media/player/thumb/dtv8yb1622023183.jpg", "out": "Marcelo Brozovic", "outPhoto": null, "reason": "injury"}, {"min": "72'", "in": "Marko Livaja", "inPhoto": "https://r2.thesportsdb.com/images/media/player/thumb/i56eg21668435990.jpg", "out": "Andrej Kramaric", "outPhoto": "https://r2.thesportsdb.com/images/media/player/thumb/bdonoc1718995936.jpg", "reason": null}, {"min": "81'", "in": "Lovro Majer", "inPhoto": "https://r2.thesportsdb.com/images/media/player/thumb/3mzm3p1653388985.jpg", "out": "Luka Modric", "outPhoto": "https://r2.thesportsdb.com/images/media/player/thumb/6j40781707595475.jpg", "reason": null}]}, "form": {"home": [{"r": "L", "score": "2-1", "opp": "KSA", "atVs": "vs", "date": "2022-11-22"}, {"r": "W", "score": "2-0", "opp": "MEX", "atVs": "vs", "date": "2022-11-26"}, {"r": "W", "score": "2-0", "opp": "POL", "atVs": "@", "date": "2022-11-30"}, {"r": "W", "score": "2-1", "opp": "AUS", "atVs": "vs", "date": "2022-12-03"}, {"r": "W", "score": "2-2", "opp": "NED", "atVs": "@", "date": "2022-12-09"}], "away": [{"r": "D", "score": "0-0", "opp": "MAR", "atVs": "@", "date": "2022-11-23"}, {"r": "W", "score": "4-1", "opp": "CAN", "atVs": "vs", "date": "2022-11-27"}, {"r": "D", "score": "0-0", "opp": "BEL", "atVs": "vs", "date": "2022-12-01"}, {"r": "W", "score": "1-1", "opp": "JPN", "atVs": "@", "date": "2022-12-05"}, {"r": "W", "score": "1-1", "opp": "BRA", "atVs": "vs", "date": "2022-12-09"}]}, "h2h": {"tally": {"w": 2, "d": 0, "l": 2}, "events": [{"date": "2018-06-21", "hs": 0, "as": 3, "r": "L"}, {"date": "2014-11-12", "hs": 2, "as": 1, "r": "W"}, {"date": "2006-03-01", "hs": 2, "as": 3, "r": "L"}, {"date": "1998-06-26", "hs": 1, "as": 0, "r": "W"}]}}