{"id": "633797", "home": {"id": "481", "name": "Germany", "tla": "GER", "crest": "https://a.espncdn.com/i/teamlogos/countries/500/ger.png", "rank": null}, "away": {"id": "627", "name": "Japan", "tla": "JPN", "crest": "https://a.espncdn.com/i/teamlogos/countries/500/jpn.png", "rank": null}, "utcDate": "2022-11-23T13:00Z", "status": "FINISHED", "score": {"home": 1, "away": 2}, "group": null, "espnMatched": true, "espnId": "633797", "events": [{"minute": "33'", "type": "Penalty - Scored", "side": "home", "player": "Ilkay G\u00fcndogan", "text": "Goal!  Germany 1, Japan 0. Ilkay G\u00fcndogan (Germany) converts the penalty with a right footed shot to the centre of the goal."}, {"minute": "75'", "type": "Goal", "side": "away", "player": "Ritsu Doan", "text": "Goal!  Germany 1, Japan 1. Ritsu Doan (Japan) left footed shot from the centre of the box to the centre of the goal."}, {"minute": "83'", "type": "Goal", "side": "away", "player": "Takuma Asano", "text": "Goal!  Germany 1, Japan 2. Takuma Asano (Japan) right footed shot from the right side of the six yard box to the top right corner. Assisted by Ko Itakura."}], "odds": null, "attendance": null, "venue": {"name": "Khalifa International Stadium", "city": "Doha", "country": "Qatar", "image": "https://services.arcgisonline.com/arcgis/rest/services/World_Imagery/MapServer/export?bbox=51.44345556,25.26201111,51.452655560000004,25.26521111&bboxSR=4326&imageSR=4326&size=1280,440&format=jpg&f=image", "capacity": null, "surface": null}, "weather": {}, "stats": {"home": {"foulsCommitted": "6", "yellowCards": "0", "redCards": "0", "offsides": "4", "wonCorners": "6", "saves": "2", "possessionPct": "73.9", "totalShots": "26", "shotsOnTarget": "9", "shotPct": "0.3", "penaltyKickGoals": "1", "penaltyKickShots": "1", "accuratePasses": "686", "totalPasses": "771", "passPct": "0.9", "accurateCrosses": "8", "totalCrosses": "25", "crossPct": "0.3", "totalLongBalls": "47", "accurateLongBalls": "28", "longballPct": "0.6", "blockedShots": "6", "effectiveTackles": "9", "totalTackles": "11", "tacklePct": "0.8", "interceptions": "3", "effectiveClearance": "3", "totalClearance": "3"}, "away": {"foulsCommitted": "14", "yellowCards": "0", "redCards": "0", "offsides": "4", "wonCorners": "6", "saves": "8", "possessionPct": "26.1", "totalShots": "12", "shotsOnTarget": "4", "shotPct": "0.3", "penaltyKickGoals": "0", "penaltyKickShots": "0", "accuratePasses": "190", "totalPasses": "269", "passPct": "0.7", "accurateCrosses": "4", "totalCrosses": "11", "crossPct": "0.4", "totalLongBalls": "54", "accurateLongBalls": "21", "longballPct": "0.4", "blockedShots": "4", "effectiveTackles": "17", "totalTackles": "29", "tacklePct": "0.6", "interceptions": "6", "effectiveClearance": "38", "totalClearance": "38"}}, "subs": {"home": [{"min": "67'", "in": "Jonas Hofmann", "inPhoto": null, "out": "Thomas M\u00fcller", "outPhoto": null, "reason": null}, {"min": "67'", "in": "Leon Goretzka", "inPhoto": "https://r2.thesportsdb.com/images/media/player/thumb/30nvkh1779382907.jpg", "out": "Ilkay G\u00fcndogan", "outPhoto": "https://r2.thesportsdb.com/images/media/player/thumb/55dcb01690988705.jpg", "reason": null}, {"min": "79'", "in": "Mario G\u00f6tze", "inPhoto": null, "out": "Jamal Musiala", "outPhoto": "https://r2.thesportsdb.com/images/media/player/thumb/y998n31779384099.jpg", "reason": null}, {"min": "79'", "in": "Niclas F\u00fcllkrug", "inPhoto": null, "out": "Kai Havertz", "outPhoto": "https://r2.thesportsdb.com/images/media/player/thumb/5c3h061780160105.jpg", "reason": null}, {"min": "90'", "in": "Youssoufa Moukoko", "inPhoto": null, "out": "Serge Gnabry", "outPhoto": null, "reason": null}], "away": [{"min": "45'", "in": "Takehiro Tomiyasu", "inPhoto": "https://r2.thesportsdb.com/images/media/player/thumb/lo0sz51678274694.jpg", "out": "Takefusa Kubo", "outPhoto": "https://r2.thesportsdb.com/images/media/player/thumb/vfxemz1696610755.jpg", "reason": null}, {"min": "57'", "in": "Kaoru Mitoma", "inPhoto": "https://r2.thesportsdb.com/images/media/player/thumb/5kog1b1772017310.jpg", "out": "Yuto Nagatomo", "outPhoto": "https://r2.thesportsdb.com/images/media/player/thumb/t21vp01608496592.jpg", "reason": null}, {"min": "57'", "in": "Takuma Asano", "inPhoto": "https://r2.thesportsdb.com/images/media/player/thumb/lll3k01724401103.jpg", "out": "Daizen Maeda", "outPhoto": "https://r2.thesportsdb.com/images/media/player/thumb/b7h2mt1668618535.jpg", "reason": null}, {"min": "71'", "in": "Ritsu Doan", "inPhoto": "https://a.espncdn.com/i/headshots/soccer/players/full/219627.png", "out": "Ao Tanaka", "outPhoto": "https://r2.thesportsdb.com/images/media/player/thumb/wwsxtv1432843083.jpg", "reason": null}, {"min": "74'", "in": "Takumi Minamino", "inPhoto": "https://r2.thesportsdb.com/images/media/player/thumb/qt6elx1578067918.jpg", "out": "Hiroki Sakai", "outPhoto": "https://r2.thesportsdb.com/images/media/player/thumb/o2hbce1668619055.jpg", "reason": "injury"}]}, "form": {"home": [{"r": "D", "score": "1-1", "opp": "HUN", "atVs": "@", "date": "2022-06-11"}, {"r": "W", "score": "5-2", "opp": "ITA", "atVs": "vs", "date": "2022-06-14"}, {"r": "L", "score": "1-0", "opp": "HUN", "atVs": "vs", "date": "2022-09-23"}, {"r": "D", "score": "3-3", "opp": "ENG", "atVs": "@", "date": "2022-09-26"}, {"r": "W", "score": "1-0", "opp": "OMA", "atVs": "@", "date": "2022-11-16"}], "away": [{"r": "W", "score": "4-1", "opp": "GHA", "atVs": "vs", "date": "2022-06-10"}, {"r": "L", "score": "3-0", "opp": "TUN", "atVs": "vs", "date": "2022-06-14"}, {"r": "W", "score": "2-0", "opp": "USA", "atVs": "vs", "date": "2022-09-23"}, {"r": "D", "score": "0-0", "opp": "ECU", "atVs": "vs", "date": "2022-09-27"}, {"r": "L", "score": "2-1", "opp": "CAN", "atVs": "vs", "date": "2022-11-17"}]}, "h2h": {"tally": {"w": 1, "d": 1, "l": 0}, "events": [{"date": "2006-05-30", "hs": 2, "as": 2, "r": "D"}, {"date": "2004-12-16", "hs": 3, "as": 0, "r": "W"}]}, "shootout": null}