{"id": "191980", "home": {"id": "481", "name": "Germany", "tla": "GER", "crest": "https://a.espncdn.com/i/teamlogos/countries/500/ger.png", "rank": null}, "away": {"id": "482", "name": "Portugal", "tla": "POR", "crest": "https://a.espncdn.com/i/teamlogos/countries/500/por.png", "rank": null}, "utcDate": "2006-07-08T19:00Z", "status": "FINISHED", "score": {"home": 3, "away": 1}, "group": null, "espnMatched": true, "espnId": "191980", "events": [{"minute": "56'", "type": "Goal", "side": "home", "player": "Bastian Schweinsteiger", "text": ""}, {"minute": "61'", "type": "Own Goal", "side": "home", "player": "Petit", "text": ""}, {"minute": "78'", "type": "Goal", "side": "home", "player": "Bastian Schweinsteiger", "text": ""}, {"minute": "88'", "type": "Goal - Header", "side": "away", "player": "Nuno Gomes", "text": ""}], "odds": null, "attendance": null, "venue": {"name": "Gottlieb-Daimler Stadion", "city": "Stuttgart", "country": "Germany", "image": null, "capacity": null, "surface": null}, "weather": {}}