{"teams": [{"idTeam": "133707", "idESPN": "176", "idAPIfootball": "81", "intLoved": "2", "strTeam": "Marseille", "strTeamAlternate": "Olympique de Marseille", "strTeamShort": "OLM", "intFormedYear": "1899", "strSport": "Soccer", "strLeague": "French Ligue 1", "idLeague": "4334", "strLeague2": "Coupe de France", "idLeague2": "4484", "strLeague3": "UEFA Europa League", "idLeague3": "4481", "strLeague4": "", "idLeague4": null, "strLeague5": "", "idLeague5": null, "strLeague6": "", "idLeague6": null, "strLeague7": "", "idLeague7": null, "strDivision": null, "idVenue": "27345", "strStadium": "Orange V\u00e9lodrome", "strKeywords": "OM", "strRSS": "", "strLocation": "Marseille, France", "intStadiumCapacity": "67394", "strWebsite": "www.om.fr", "strFacebook": "www.facebook.com/OM", "strTwitter": "twitter.com/OM_Officiel", "strInstagram": "instagram.com/olympiquedemarseille", "strDescriptionEN": "Olympique de Marseille (also known as l'OM IPA: , locally ) or simply Marseille, is a French association football club based in Marseille.\r\n\r\nFounded in 1899, the club play in Ligue 1 and have spent most of their history in the top tier of French football. Marseille have been French champions ten times (nine times in Ligue 1) and have won the Coupe de France a record ten times. In 1993, the club became the first and only French club to win the UEFA Champions League. In 1994, Marseille were relegated because of a bribery scandal, losing their domestic trophy, but not the UEFA Champions League title. In 2010, Marseille became French champions again, under the stewardship of former club captain Didier Deschamps.\r\n\r\nMarseille's home ground is the 67,000-person-capacity Stade V\u00e9lodrome located in the southern part of the city, where they have played since 1937. The Stade V\u00e9lodrome is renowned for its lively atmosphere. The club have a large fan-base having regularly averaged the highest all-time attendance in French football. Marseille's average home gate for the 2008\u201309 season was 52,276, the highest in Ligue 1. The stadium underwent renovation in 2011, going from its previous capacity of 60,031 to 42,000. Following completion in August 2014, the final capacity will be 67,000 ahead of France's hosting of UEFA Euro 2016. The club is sixteenth globally in terms of annual revenue, generating \u20ac135.7 million in 2012.\r\n\r\nIn 1997, Marseille was purchased by Franco-Swiss businessman Robert Louis-Dreyfus. Following the death of Louis-Dreyfus, his widow Margarita became the club's majority shareholder in 2010.", "strDescriptionDE": null, "strDescriptionFR": "L'Olympique de Marseille (OM) est un club de football fran\u00e7ais fond\u00e9 en ao\u00fbt 1899 par Ren\u00e9 Dufaure de Montmirail. Neuf titres de championnat de France professionnel, dix Coupes de France, trois Coupes de la Ligue, deux Troph\u00e9es des champions et une Ligue des champions de l'UEFA composent le palmar\u00e8s du club le plus titr\u00e9 et le plus populaire du football fran\u00e7ais1.\r\n\r\nLe club joue au stade de l'Huveaune de 1904 \u00e0 1937, date \u00e0 laquelle est inaugur\u00e9 le stade V\u00e9lodrome. Auparavant, le club marseillais remporte sa premi\u00e8re Coupe de France en 1924 et devient le tout premier club provincial \u00e0 s'adjuger ce titre.\r\n\r\nMarseille est l'un des clubs qui a jou\u00e9 durant la saison inaugurale 1932-1933 et qui \u00e9volue encore en Ligue 1 aujourd'hui. L'OM remporte son premier Championnat en 1937, avant de descendre pour la premi\u00e8re fois en seconde division en 1959. Une s\u00e9rie de mont\u00e9es et descentes s'effectue dans les ann\u00e9es 1960 et la d\u00e9cennie suivante est marqu\u00e9e par le premier doubl\u00e9 Coupe-Championnat de l'histoire du club en 1972.\r\n\r\nApr\u00e8s une p\u00e9riode noire aux d\u00e9buts des ann\u00e9es 1980 o\u00f9 l'OM est proche de la faillite, l'arriv\u00e9e de Bernard Tapie introduit la p\u00e9riode la plus faste du club, avec quatre titres de champion cons\u00e9cutifs, une Coupe de France et la Ligue des champions 1992-1993, qui reste la seule remport\u00e9e par un club fran\u00e7ais. L'affaire VA-OM et ses cons\u00e9quences \u00e9conomiques plongent le club en deuxi\u00e8me division. Depuis sa remont\u00e9e en 1996, le club se confronte \u00e0 nouveau \u00e0 la justice avec l'affaire des comptes de l'OM et n'arrive plus \u00e0 gagner de titre majeur, malgr\u00e9 notamment deux finales de Coupe UEFA (1999 et 2004). Cette p\u00e9riode blanche prend fin avec le titre de champion de France 2009-2010 et trois victoires cons\u00e9cutives en Coupe de la Ligue en 2010, 2011 et 2012.\r\n\r\nLe club est depuis 2011 pr\u00e9sid\u00e9 par Vincent Labrune, l'actionnaire principale \u00e9tant Margarita Louis-Dreyfus, veuve de Robert Louis-Dreyfus. L'\u00e9quipe premi\u00e8re, entra\u00een\u00e9e par Marcelo Bielsa depuis le 21 mai 2014, \u00e9volue lors de la saison 2014-2015 en premi\u00e8re division fran\u00e7aise pour la soixante-cinqui\u00e8me fois de son histoire.", "strDescriptionCN": null, "strDescriptionIT": "L'Olympique de Marseille, noto in italiano come Olympique Marsiglia o semplicemente Marsiglia, \u00e8 una societ\u00e0 calcistica francese con sede nella citt\u00e0 di Marsiglia, militante in Ligue 1, la massima divisione del campionato francese di calcio. Gioca le proprie partite casalinghe allo stadio V\u00e9lodrome, impianto da oltre 67 000 posti a sedere.\r\n\r\nOltre a essere una delle compagini pi\u00f9 titolate del paese, grazie alla vittoria di nove campionati, dieci coppe, tre Coppe di Lega e tre supercoppe nazionali, nonch\u00e9 la squadra che vanta il maggior numero di partecipazioni alla massima serie (71), \u00e8 l'unico club francese a essersi laureato campione d'Europa, avendo vinto la UEFA Champions League nella stagione 1992-1993. Insieme al Paris Saint-Germain \u00e8 anche uno dei due soli club transalpini ad avere vinto una competizione calcistica europea stagionale.\r\n\r\nCon il Paris Saint-Germain partecipa a una delle rivalit\u00e0 pi\u00f9 sentite del calcio francese, denominata le Classique.", "strDescriptionJP": null, "strDescriptionRU": null, "strDescriptionES": null, "strDescriptionPT": null, "strDescriptionSE": null, "strDescriptionNL": null, "strDescriptionHU": null, "strDescriptionNO": null, "strDescriptionIL": null, "strDescriptionPL": null, "strColour1": "#00A1DF", "strColour2": "#FFFFFF", "strColour3": "#bea064", "strGender": "Male", "strCountry": "France", "strBadge": "https://r2.thesportsdb.com/images/media/team/badge/c6bazh1779212287.png", "strLogo": "https://r2.thesportsdb.com/images/media/team/logo/zgx7kp1548937902.png", "strFanart1": "https://r2.thesportsdb.com/images/media/team/fanart/o29qlc1731826749.jpg", "strFanart2": "https://r2.thesportsdb.com/images/media/team/fanart/uxvyqt1420732162.jpg", "strFanart3": "https://r2.thesportsdb.com/images/media/team/fanart/tsrsyq1420731904.jpg", "strFanart4": "https://r2.thesportsdb.com/images/media/team/fanart/vrtwxy1420731838.jpg", "strBanner": "https://r2.thesportsdb.com/images/media/team/banner/rutppp1420732910.jpg", "strEquipment": "https://r2.thesportsdb.com/images/media/team/equipment/pok6qa1766154284.png", "strYoutube": "www.youtube.com/user/OM", "strLocked": "unlocked"}]}